homebrew.py
erix_python_utils-0.0.12.dist-info/LICENSE
erix_python_utils-0.0.12.dist-info/METADATA
erix_python_utils-0.0.12.dist-info/WHEEL
erix_python_utils-0.0.12.dist-info/top_level.txt
erix_python_utils-0.0.12.dist-info/RECORD
