Metadata-Version: 2.1
Name: erix-python-utils
Version: 0.0.12
Summary: All of my utilities and tools in one place
Home-page: UNKNOWN
Author: Eric Stratigakis
Author-email: enstrati@uwaterloo.ca
License: UNKNOWN
Platform: UNKNOWN
Classifier: Development Status :: 1 - Planning
Classifier: Operating System :: OS Independent
Classifier: Programming Language :: Python :: 3
Classifier: License :: OSI Approved :: MIT License
Requires-Python: >=3
Requires-Dist: requests
